VpostHorde/__init__.py
VpostHorde/__main__.py
VpostHorde/main.py
VpostHorde/tools/Analisis.py
VpostHorde/tools/Consola.py
VpostHorde/tools/Estres.py
VpostHorde/tools/GUI.py
VpostHorde/tools/Peticion.py
VpostHorde/tools/__init__.py
VpostHorde/tools/plot.py
VpostHorde-0.9.2.dist-info/METADATA
VpostHorde-0.9.2.dist-info/WHEEL
VpostHorde-0.9.2.dist-info/entry_points.txt
VpostHorde-0.9.2.dist-info/top_level.txt
VpostHorde-0.9.2.dist-info/RECORD
