Metadata-Version: 2.1
Name: VpostHorde
Version: 0.9.2
Summary: Web stress test
Home-page: https://github.com/ValdrST/VpostHorde
Author: Valdr Stiglitz
Author-email: valdr.stiglitz@gmail.com
License: UNKNOWN
Platform: UNKNOWN
Classifier: Programming Language :: Python :: 3
Classifier: Operating System :: OS Independent
Requires-Dist: requests (==2.22.0)
Requires-Dist: wxPython (==4.0.5)
Requires-Dist: numpy (==1.16.4)
Requires-Dist: pip (==19.0.3)
Requires-Dist: setuptools (==41.0.1)
